Metadata-Version: 1.1
Name: opsimulate
Version: 0.0.4
Summary: Tool/Framework for simulating operations problems/incidents
Home-page: https://github.com/RochesterinNYC/opsimulate
Author: James Wen
Author-email: jrw2175@columbia.edu
License: UNKNOWN
Platform: UNKNOWN
Classifier: Development Status :: 1 - Planning
Classifier: Natural Language :: English
Classifier: Operating System :: MacOS :: MacOS X
Classifier: Programming Language :: Python
Classifier: Programming Language :: Python :: 2
Classifier: Programming Language :: Python :: 2.7
Classifier: Programming Language :: Python :: Implementation :: CPython
Classifier: Topic :: Software Development :: Libraries :: Python Modules
